meshcore/__init__.py
meshcore/ble_cx.py
meshcore/connection_manager.py
meshcore/events.py
meshcore/lpp_json_encoder.py
meshcore/meshcore.py
meshcore/packets.py
meshcore/parsing.py
meshcore/reader.py
meshcore/serial_cx.py
meshcore/tcp_cx.py
meshcore/commands/__init__.py
meshcore/commands/base.py
meshcore/commands/binary.py
meshcore/commands/contact.py
meshcore/commands/control_data.py
meshcore/commands/device.py
meshcore/commands/messaging.py
meshcore-2.2.5.dist-info/METADATA
meshcore-2.2.5.dist-info/WHEEL
meshcore-2.2.5.dist-info/licenses/LICENSE
meshcore-2.2.5.dist-info/RECORD
