Metadata-Version: 2.4
Name: meshcore
Version: 2.2.5
Summary: Base classes for communicating with meshcore companion radios
Project-URL: Homepage, https://github.com/fdlamotte/meshcore_py
Project-URL: Issues, https://github.com/fdlamotte/meshcore_py/issues
Author-email: Florent de Lamotte <florent@frizoncorrea.fr>, Alex Wolden <awolden@gmail.com>
License-Expression: MIT
License-File: LICENSE
Classifier: Operating System :: OS Independent
Classifier: Programming Language :: Python :: 3
Requires-Python: >=3.10
Requires-Dist: bleak
Requires-Dist: pycayennelpp
Requires-Dist: pyserial-asyncio-fast
Provides-Extra: dev
Requires-Dist: black; extra == 'dev'
Requires-Dist: pytest; extra == 'dev'
Requires-Dist: pytest-asyncio; extra == 'dev'
Requires-Dist: ruff; extra == 'dev'
